buildout.cfg
setup.py
src/zc/__init__.py
src/zc.monitorcache.egg-info/PKG-INFO
src/zc.monitorcache.egg-info/SOURCES.txt
src/zc.monitorcache.egg-info/dependency_links.txt
src/zc.monitorcache.egg-info/namespace_packages.txt
src/zc.monitorcache.egg-info/not-zip-safe
src/zc.monitorcache.egg-info/requires.txt
src/zc.monitorcache.egg-info/top_level.txt
src/zc/monitorcache/README.txt
src/zc/monitorcache/__init__.py
src/zc/monitorcache/configure.zcml
src/zc/monitorcache/tests.py