Metadata-Version: 1.0
Name: zc.monitorcache
Version: 0.1.0
Summary: zc.monitor plugin to modify cache sizes
Home-page: UNKNOWN
Author: Alex Chapman
Author-email: achapman@zope.com
License: ZPL 2.1
Platform: UNKNOWN
